setup.py
src/digimat/__init__.py
src/digimat.simpletimer.egg-info/PKG-INFO
src/digimat.simpletimer.egg-info/SOURCES.txt
src/digimat.simpletimer.egg-info/dependency_links.txt
src/digimat.simpletimer.egg-info/namespace_packages.txt
src/digimat.simpletimer.egg-info/not-zip-safe
src/digimat.simpletimer.egg-info/requires.txt
src/digimat.simpletimer.egg-info/top_level.txt
src/digimat/simpletimer/__init__.py
src/digimat/simpletimer/simpletimer.py