Metadata-Version: 1.0
Name: digimat.simpletimer
Version: 0.0.1
Summary: Digimat Simple Timers
Home-page: UNKNOWN
Author: Frederic Hess
Author-email: fhess@splust.ch
License: PSF
Platform: UNKNOWN
